<Root><Products><Product><Vendor>Makina</Vendor><Language>tr</Language><Productname>Xenon UV Bask&#305; Makinesi / Xenon UV Printing Machine</Productname><Productcode>#00191741</Productcode><Category>UV Bask&#305; Makinas&#305;</Category><Brand>Xenon Lazer</Brand><Modeltype>Sat&#305;l&#305;k</Modeltype><Origin>T&#252;rkiye</Origin><Delivery_status>Stokta Var</Delivery_status><Guarantee>1 Y&#305;l Garantili</Guarantee><Price>13.000</Price><Price_Description>+KDV Min. Sipari&#351; 1 Adet</Price_Description><Phone>+902125505565</Phone><Whatsapp>+905444384024</Whatsapp><Description>&lt;div id="aciklama" class="clearfix tab-pane fade in active"&gt;&lt;p&gt;&lt;h2&gt;&lt;strong&gt;Xenon Lazer&#160;&lt;/strong&gt;&lt;/h2&gt;&lt;h2&gt;&lt;strong&gt;Xenon UV Bask&#305; Makinesi / Xenon UV Printing Machine&lt;/strong&gt;&lt;/h2&gt;&lt;p&gt;&#160;UV BASKI MAK&#304;NES&#304; TEKN&#304;K &#214;ZELL&#304;KLER&#304;&lt;/p&gt;&lt;table cellspacing="0"&gt;&lt;tbody&gt;&lt;tr&gt;&lt;td&gt;&lt;p&gt;BASKI ALANI&lt;/p&gt;&lt;/td&gt;&lt;td&gt;&lt;p&gt;:&lt;/p&gt;&lt;/td&gt;&lt;td&gt;&lt;p&gt;90 x 60cm&lt;/p&gt;&lt;/td&gt;&lt;/tr&gt;&lt;tr&gt;&lt;td&gt;&lt;p&gt;BASKI YUKSEKL&#304;&#286;&#304;&#160; &#160;&lt;/p&gt;&lt;/td&gt;&lt;td&gt;&lt;p&gt;:&lt;/p&gt;&lt;/td&gt;&lt;td&gt;&lt;p&gt;15CM&lt;/p&gt;&lt;/td&gt;&lt;/tr&gt;&lt;tr&gt;&lt;td&gt;&lt;p&gt;BASKI PROGRAMI&#160; &#160;&lt;/p&gt;&lt;/td&gt;&lt;td&gt;&lt;p&gt;:&lt;/p&gt;&lt;/td&gt;&lt;td&gt;&lt;p&gt;PHOTO PRINT&lt;/p&gt;&lt;/td&gt;&lt;/tr&gt;&lt;tr&gt;&lt;td&gt;&lt;p&gt;BASKI KAFASI&lt;/p&gt;&lt;/td&gt;&lt;td&gt;&lt;p&gt;:&lt;/p&gt;&lt;/td&gt;&lt;td&gt;&lt;p&gt;3 ADET TX800&lt;/p&gt;&lt;/td&gt;&lt;/tr&gt;&lt;tr&gt;&lt;td&gt;&lt;p&gt;RENK SIRALAMASI&lt;/p&gt;&lt;/td&gt;&lt;td&gt;&lt;p&gt;:&lt;/p&gt;&lt;/td&gt;&lt;td&gt;&lt;p&gt;CMYKLCLM+W+V&lt;/p&gt;&lt;p&gt;(6 ANA RENK + BEYAZ + LAK )&lt;/p&gt;&lt;/td&gt;&lt;/tr&gt;&lt;tr&gt;&lt;td&gt;&lt;p&gt;TABLA S&#304;STEM&#304;&#160; &#160; &#160; &#160;&lt;/p&gt;&lt;/td&gt;&lt;td&gt;&lt;p&gt;:&lt;/p&gt;&lt;/td&gt;&lt;td&gt;&lt;p&gt;VAKUMLU TABLA&lt;/p&gt;&lt;/td&gt;&lt;/tr&gt;&lt;tr&gt;&lt;td&gt;&lt;p&gt;BOYA TANK&#160; &#160; &#160; &#160; &#160; &#160;&lt;/p&gt;&lt;/td&gt;&lt;td&gt;&lt;p&gt;:&lt;/p&gt;&lt;/td&gt;&lt;td&gt;&lt;p&gt;BOYA DONMA &#214;NLEY&#304;C&#304; &#199;ALKALAMA S&#304;STEM&#304;&lt;/p&gt;&lt;/td&gt;&lt;/tr&gt;&lt;tr&gt;&lt;td&gt;&lt;p&gt;UYARI S&#304;STEM&#304;&lt;/p&gt;&lt;/td&gt;&lt;td&gt;&lt;p&gt;:&lt;/p&gt;&lt;/td&gt;&lt;td&gt;&lt;p&gt;BOYA B&#304;T&#304;&#350; UYARI S&#304;STEM&#304;&lt;/p&gt;&lt;/td&gt;&lt;/tr&gt;&lt;tr&gt;&lt;td&gt;&lt;p&gt;LED LAMBA SAYISI&lt;/p&gt;&lt;/td&gt;&lt;td&gt;&lt;p&gt;:&lt;/p&gt;&lt;/td&gt;&lt;td&gt;&lt;p&gt;3 ADET&lt;/p&gt;&lt;/td&gt;&lt;/tr&gt;&lt;tr&gt;&lt;td&gt;&lt;p&gt;MALZEME Y&#220;KSEKL&#304;K&#160;AYARI&lt;/p&gt;&lt;/td&gt;&lt;td&gt;&lt;p&gt;:&lt;/p&gt;&lt;/td&gt;&lt;td&gt;&lt;p&gt;&#160;&lt;/p&gt;&lt;p&gt;OTOMAT&#304;K&lt;/p&gt;&lt;p&gt;&#160;&lt;/p&gt;&lt;/td&gt;&lt;/tr&gt;&lt;/tbody&gt;&lt;/table&gt;&lt;p&gt;&#160;&lt;/p&gt;&lt;p&gt;&#160;UV PRINTING MACHINE TECHNICAL SPECIFICATIONS&lt;/p&gt;&lt;div&gt;&lt;table border="1" cellspacing="0"&gt;&lt;tbody&gt;&lt;tr&gt;&lt;td&gt;&lt;p&gt;PRINT AREA&lt;/p&gt;&lt;/td&gt;&lt;td&gt;&lt;p&gt;:&lt;/p&gt;&lt;/td&gt;&lt;td&gt;&lt;p&gt;90 x 60cm&lt;/p&gt;&lt;/td&gt;&lt;/tr&gt;&lt;tr&gt;&lt;td&gt;&lt;p&gt;PRINT HEIGHT&#160; &#160;&lt;/p&gt;&lt;/td&gt;&lt;td&gt;&lt;p&gt;:&lt;/p&gt;&lt;/td&gt;&lt;td&gt;&lt;p&gt;15CM&lt;/p&gt;&lt;/td&gt;&lt;/tr&gt;&lt;tr&gt;&lt;td&gt;&lt;p&gt;PRINT PROGRAM&#160; &#160;&lt;/p&gt;&lt;/td&gt;&lt;td&gt;&lt;p&gt;:&lt;/p&gt;&lt;/td&gt;&lt;td&gt;&lt;p&gt;PHOTO PRINT&lt;/p&gt;&lt;/td&gt;&lt;/tr&gt;&lt;tr&gt;&lt;td&gt;&lt;p&gt;PRINT HEAD&lt;/p&gt;&lt;/td&gt;&lt;td&gt;&lt;p&gt;:&lt;/p&gt;&lt;/td&gt;&lt;td&gt;&lt;p&gt;3 PCS TX800&lt;/p&gt;&lt;/td&gt;&lt;/tr&gt;&lt;tr&gt;&lt;td&gt;&lt;p&gt;COLOR RANKING&lt;/p&gt;&lt;/td&gt;&lt;td&gt;&lt;p&gt;:&lt;/p&gt;&lt;/td&gt;&lt;td&gt;&lt;p&gt;CMYKLCLM+W+V&lt;/p&gt;&lt;p&gt;(6 MAIN COLOR + WHITE + LACQUER )&lt;/p&gt;&lt;/td&gt;&lt;/tr&gt;&lt;tr&gt;&lt;td&gt;&lt;p&gt;TABLE SYSTEM&#160; &#160; &#160; &#160;&lt;/p&gt;&lt;/td&gt;&lt;td&gt;&lt;p&gt;:&lt;/p&gt;&lt;/td&gt;&lt;td&gt;&lt;p&gt;VACUUM TABLE&lt;/p&gt;&lt;/td&gt;&lt;/tr&gt;&lt;tr&gt;&lt;td&gt;&lt;p&gt;PAINT TANK&#160; &#160; &#160; &#160; &#160; &#160;&lt;/p&gt;&lt;/td&gt;&lt;td&gt;&lt;p&gt;:&lt;/p&gt;&lt;/td&gt;&lt;td&gt;&lt;p&gt;PAINT ANTI-FROST RINSE SYSTEM&lt;/p&gt;&lt;/td&gt;&lt;/tr&gt;&lt;tr&gt;&lt;td&gt;&lt;p&gt;WARNING SYSTEM&lt;/p&gt;&lt;/td&gt;&lt;td&gt;&lt;p&gt;:&lt;/p&gt;&lt;/td&gt;&lt;td&gt;&lt;p&gt;PAINT FINISH WARNING SYSTEM&lt;/p&gt;&lt;/td&gt;&lt;/tr&gt;&lt;tr&gt;&lt;td&gt;&lt;p&gt;NUMBER OF LED LAMPS&lt;/p&gt;&lt;/td&gt;&lt;td&gt;&lt;p&gt;:&lt;/p&gt;&lt;/td&gt;&lt;td&gt;&lt;p&gt;3 PIECES&lt;/p&gt;&lt;/td&gt;&lt;/tr&gt;&lt;tr&gt;&lt;td&gt;&lt;p&gt;MATERIAL HEIGHT&#160;&#160;ADJUSTMENT&lt;/p&gt;&lt;/td&gt;&lt;td&gt;&lt;p&gt;:&lt;/p&gt;&lt;/td&gt;&lt;td&gt;&lt;p&gt;&#160;&lt;/p&gt;&lt;p&gt;AUTOMATIC&lt;/p&gt;&lt;p&gt;&#160;&lt;/p&gt;&lt;/td&gt;&lt;/tr&gt;&lt;/tbody&gt;&lt;/table&gt;&lt;/div&gt;&lt;/p&gt;&lt;/div&gt;</Description><Images><image0>https://127.0.0.1:8000/media/temp/images/di31AYi2v7mUz0WWAD7lImtETyc4ysJ6lia.jpg</image0><image1>https://127.0.0.1:8000/media/temp/images/e8VI66fI562DsD5GECpd4K2fNUsXOUgUsQR.jpg</image1><image2>https://127.0.0.1:8000/media/temp/images/cO6rYEJfWzXAEDlQ63pmoITtZKGZxqqdDOL.jpg</image2><image3>https://127.0.0.1:8000/media/temp/images/xXOiAAzm28xCixYJjcttGAv7IXSpjQW60dO.jpg</image3><image4>https://127.0.0.1:8000/media/temp/images/wAyEvhd8lI4RoOEYRjL9AQc8u0Ujq6KCBSf.jpg</image4><image5>https://127.0.0.1:8000/media/temp/images/603AbqrGtZ8qyLoPtT8NUlv5wUf8LCLEtAC.jpg</image5><image6>https://127.0.0.1:8000/media/temp/images/yRHQfx2zVpcwgTCd5R4oTmvlhlMGQVqh8yt.jpg</image6><image7>https://127.0.0.1:8000/media/temp/images/kckZz6n9fDOUICnSYTBOrqA358uLtcXxJ4z.jpg</image7></Images></Product></Products><Last_update>22-02-2023 09:20 PM</Last_update></Root>